Metadata-Version: 2.1
Name: os-tflite-simple-cv
Version: 1.0.0
Summary: Simple demo for my OS course project, 
Home-page: UNKNOWN
Author: TK Luong
Author-email: 
License: MIT
Platform: UNKNOWN
Classifier: License :: OSI Approved :: MIT License
Classifier: Programming Language :: Python :: 3
Classifier: Programming Language :: Python :: 3.7
